[
  {
    "name": "Setup",
    "module": "Cardinal",
    "defaultConfig": {
      "Roles": {
        "feather": "Role",
        "form": {
          "attrs": ["name", "description", "createdBy", "updated", "updatedBy"]
        },
        "list": {
          "attrs": ["name", "description", "createdBy", "updated", "updatedBy"]
        }
      }
    }
  },
  {
    "name": "BackOffice",
    "module": "Cardinal",
    "defaultConfig": {
      "Contacts": {
        "feather": "Contact",
        "form": {
          "attrs": ["name", "isActive", "email", "birthDate", "workPhone",
            "homePhone", "annualIncome", "creditScore", "role", "created",
            "createdBy", "updated", "updatedBy", "objectType"]
        },
        "list": {
          "attrs": ["name", "email", "isActive", "birthDate", "workPhone",
            "homePhone", "creditScore", "objectType"]
        }
      },
      "Activities": {
        "feather": "Activity",
        "form": {
          "attrs": ["name", "description", "startDate", "dueDate",
            "priority", "isCompleted", "objectType",
            "created", "createdBy", "updated", "updatedBy"]
        },
        "list": {
          "attrs": ["name", "description", "startDate", "dueDate",
            "priority", "isCompleted", "objectType",
            "created", "createdBy", "updated", "updatedBy"]
        }
      },
      "Task": {
        "feather": "Task",
        "form": {
          "attrs": ["name", "description", "startDate", "dueDate",
            "priority", "isCompleted",
            "created", "createdBy", "updated", "updatedBy"]
        },
        "list": {
          "attrs": ["name", "description", "startDate", "dueDate",
            "priority", "isCompleted",
            "created", "createdBy", "updated", "updatedBy"]
        }
      }
    }
  },
  {
    "name": "Sales",
    "module": "Cardinal",
    "defaultConfig": {
      "Contacts": {
        "feather": "Contact",
        "form": {
          "attrs": ["name", "isActive", "email", "birthDate", "workPhone",
            "homePhone", "annualIncome", "creditScore", "role", "created",
            "createdBy", "updated", "updatedBy", "objectType"]
        },
        "list": {
          "attrs": ["name", "email", "isActive", "birthDate", "workPhone",
            "homePhone", "creditScore", "objectType"]
        }
      },
      "Leads": {
        "feather": "Lead",
        "form": {
          "attrs": ["company", "name", "isActive", "email", "birthDate",
            "workPhone", "homePhone", "annualIncome", "creditScore", "role",
            "probability", "opportunity", "remarks", "created", "createdBy",
            "updated", "updatedBy"]
        },
        "list": {
          "attrs": ["company", "name", "email", "isActive", "birthDate",
            "workPhone", "probability", "homePhone", "creditScore"]
        }
      },
      "Opportunities": {
        "feather": "Opportunity",
        "form": {
          "attrs": ["number", "name", "description", "startDate", "dueDate",
            "amount", "stage", "priority", "isCompleted",
            "created", "createdBy", "updated", "updatedBy"]
        },
        "list": {
          "attrs": ["number", "name", "description", "startDate", "dueDate",
            "amount", "stage", "priority", "isCompleted",
            "created", "createdBy", "updated", "updatedBy"]
        }
      }
    }
  }
]
