[
    {
        "name": "AmazonProduct",
        "plural": "AmazonProducts",
        "module": "Amazon",
        "description": "Amazon products",
        "inherits": "Product",
        "properties": {
            "asin": {
                "description": "Material",
                "type": "string"
            },
            "sellerRank": {
                "description": "Best seller rank",
                "type": "number"
            },
            "shippingWeight": {
                "description": "Shipping weight, pounds",
                "type": "number"
            },
            "productDescription": {
                "description": "Published product description",
                "type": "string"
            }
        }
    },
    {
        "name": "Frame",
        "plural": "Frames",
        "module": "Amazon",
        "description": "Bicycle frames",
        "inherits": "AmazonProduct",
        "properties": {
            "material": {
                "description": "Material",
                "type": "string"
            },
            "color": {
                "description": "Color",
                "type": "string"
            },           
            "bottomBracket": {
                "description": "Bottom bracket types",
                "type": "string"
            },
            "fork": {
                "description": "Frame fork type",
                "type": "string"
            },
            "front": {
                "description": "Front type",
                "type": "string"
            },
            "seatPost": {
                "description": "Seat post size",
                "type": "string"
            },
            "weight": {
                "description": "Weight, grams",
                "type": "number"
            }
        }
    }, 
    {
        "name": "Seat",
        "plural": "Seats",
        "module": "Amazon",
        "description": "Bicycle seats",
        "inherits": "AmazonProduct",
        "properties": {
            "color": {
                "description": "Color",
                "type": "string"
            },
            "style": {
                "description": "Seat style",
                "type": "string"
            },
            "weight": {
                "description": "Weight, grams",
                "type": "number"
            }
        }
    }, 
    {
        "name": "Wheel",
        "plural": "Wheels",
        "module": "Amazon",
        "description": "Bicycle wheel",
        "inherits": "AmazonProduct",
        "properties": {
            "material": {
                "description": "Material",
                "type": "string"
            },
            "diameter": {
                "description": "Diameter, inches",
                "type": "number"
            },
            "width": {
                "description": "Width",
                "type": "number"
            },
            "hub": {
                "description": "Hub type",
                "type": "string"
            },
            "style": {
                "description": "Wheel style",
                "type": "string"
            },
            "weight": {
                "description": "Weight, grams",
                "type": "number"
            }
        }
    },
    {
        "name": "Bicycle",
        "plural": "Bicycles",
        "module": "Amazon",
        "description": "Bicycles",
        "inherits": "AmazonProduct",
        "properties": {
            "frameMaterial": {
                "description": "Material",
                "type": "string"
            },
            "color": {
                "description": "Color",
                "type": "string"
            },
            "size": {
                "description": "Downtube length, inches",
                "type": "number"
            },
            "hub": {
                "description": "Hub type",
                "type": "string"
            },
            "gearSet": {
                "description": "Gear set",
                "type": "string"
            },
            "style": {
                "description": "Style",
                "type": "string"
            },
            "weight": {
                "description": "Weight, pounds",
                "type": "number"
            }
        }
    }
]
